git_tips/__init__.py
git_tips/__main__.py
git_tips_cli-0.1.0.dist-info/licenses/LICENSE
git_tips_cli-0.1.0.dist-info/METADATA
git_tips_cli-0.1.0.dist-info/WHEEL
git_tips_cli-0.1.0.dist-info/entry_points.txt
git_tips_cli-0.1.0.dist-info/top_level.txt
git_tips_cli-0.1.0.dist-info/RECORD
